Metadata-Version: 2.4
Name: pywa
Version: 3.7.0
Summary: 🚀 Build WhatsApp Bots in Python • Fast, Effortless, Powerful
Author-email: David Lev <david@davidlev.dev>
License: MIT
Project-URL: Documentation, https://pywa.readthedocs.io/
Project-URL: Issue Tracker, https://github.com/david-lev/pywa/issues
Project-URL: Source Code, https://github.com/david-lev/pywa
Project-URL: Funding, https://github.com/sponsors/david-lev
Project-URL: Changelog, https://github.com/david-lev/pywa/blob/master/CHANGELOG.md
Keywords: whatsapp,whatsapp-api,whatsapp-cloud-api,whatsapp-cloud,whatsapp-api-python,whatsapp-cloud-api-python,pywa,wapy,wa,wa-api,wa-cloud-api,wa-cloud,wa-api-python,wa-cloud-api-python,whatsapp-webhook,whatsapp-webhook-python,whatsapp-webhook-api,whatsapp-flows,whatsapp-cloud-api-flows
Classifier: Topic :: Communications :: Chat
Classifier: Topic :: Communications
Classifier: Topic :: Utilities
Classifier: Development Status :: 5 - Production/Stable
Classifier: Intended Audience :: Developers
Classifier: License :: OSI Approved :: MIT License
Classifier: Operating System :: OS Independent
Classifier: Topic :: Internet
Classifier: Topic :: Software Development :: Libraries
Classifier: Topic :: Software Development :: Libraries :: Python Modules
Classifier: Topic :: Software Development :: Libraries :: Application Frameworks
Requires-Python: >=3.10
License-File: LICENSE
Requires-Dist: httpx>=0.27.0
Provides-Extra: flask
Requires-Dist: flask[async]; extra == "flask"
Provides-Extra: fastapi
Requires-Dist: fastapi[standard]; extra == "fastapi"
Provides-Extra: cryptography
Requires-Dist: cryptography; extra == "cryptography"
Dynamic: license-file
